<?xml version="1.0" encoding="utf-8"?>
<TextureAtlas imagePath="killer-sans-funny-phase-1.png">
	<!-- Created with Adobe Animate version 20.0.0.17400 -->
	<!-- http://www.adobe.com/products/animate.html -->
	<SubTexture name="Sans down0000" x="6611" y="1998" width="489" height="607"/>
	<SubTexture name="Sans down0001" x="7120" y="2602" width="489" height="607"/>
	<SubTexture name="Sans down0002" x="7629" y="2602" width="489" height="607"/>
	<SubTexture name="Sans down0003" x="6611" y="2625" width="489" height="607"/>
	<SubTexture name="Sans down0004" x="20" y="2637" width="489" height="607"/>
	<SubTexture name="Sans down0005" x="529" y="2637" width="489" height="607"/>
	<SubTexture name="Sans down0006" x="1038" y="2637" width="489" height="607"/>
	<SubTexture name="Sans down0007" x="1547" y="2637" width="489" height="607"/>
	<SubTexture name="Sans down0008" x="2056" y="2637" width="489" height="607"/>
	<SubTexture name="Sans down0009" x="2565" y="2637" width="489" height="607"/>
	<SubTexture name="Sans down0010" x="3074" y="2637" width="489" height="607"/>
	<SubTexture name="Sans down0011" x="3583" y="2637" width="489" height="607"/>
	<SubTexture name="Sans down0012" x="4092" y="2637" width="489" height="607"/>
	<SubTexture name="Sans idle0000" x="7475" y="669" width="500" height="619"/>
	<SubTexture name="Sans idle0001" x="7475" y="1308" width="500" height="619"/>
	<SubTexture name="Sans idle0002" x="20" y="1343" width="500" height="619"/>
	<SubTexture name="Sans idle0003" x="540" y="1343" width="500" height="619"/>
	<SubTexture name="Sans idle0004" x="1060" y="1343" width="500" height="619"/>
	<SubTexture name="Sans idle0005" x="1580" y="1343" width="500" height="619"/>
	<SubTexture name="Sans idle0006" x="2100" y="1343" width="500" height="619"/>
	<SubTexture name="Sans idle0007" x="2620" y="1343" width="500" height="619"/>
	<SubTexture name="Sans idle0008" x="3140" y="1343" width="500" height="619"/>
	<SubTexture name="Sans idle0009" x="3660" y="1343" width="500" height="619"/>
	<SubTexture name="Sans idle0010" x="4180" y="1343" width="500" height="619"/>
	<SubTexture name="Sans idle0011" x="4700" y="1343" width="500" height="619"/>
	<SubTexture name="Sans idle0012" x="5220" y="1343" width="500" height="619"/>
	<SubTexture name="Sans idle0013" x="5740" y="1343" width="500" height="619"/>
	<SubTexture name="Sans idle0014" x="6260" y="1343" width="500" height="619"/>
	<SubTexture name="Sans left0000" x="20" y="20" width="513" height="629"/>
	<SubTexture name="Sans left0001" x="553" y="20" width="513" height="629"/>
	<SubTexture name="Sans left0002" x="1086" y="20" width="513" height="629"/>
	<SubTexture name="Sans left0003" x="1619" y="20" width="513" height="629"/>
	<SubTexture name="Sans left0004" x="2152" y="20" width="513" height="629"/>
	<SubTexture name="Sans left0005" x="2685" y="20" width="513" height="629"/>
	<SubTexture name="Sans left0006" x="3218" y="20" width="513" height="629"/>
	<SubTexture name="Sans left0007" x="3751" y="20" width="513" height="629"/>
	<SubTexture name="Sans left0008" x="4284" y="20" width="513" height="629"/>
	<SubTexture name="Sans left0009" x="4817" y="20" width="513" height="629"/>
	<SubTexture name="Sans left0010" x="5350" y="20" width="513" height="629"/>
	<SubTexture name="Sans left0011" x="5883" y="20" width="513" height="629"/>
	<SubTexture name="Sans left0012" x="6416" y="20" width="513" height="629"/>
	<SubTexture name="Sans left0013" x="6949" y="20" width="513" height="629"/>
	<SubTexture name="Sans left0014" x="7482" y="20" width="513" height="629"/>
	<SubTexture name="Sans right0000" x="6780" y="1343" width="487" height="635"/>
	<SubTexture name="Sans right0001" x="7287" y="1947" width="487" height="635"/>
	<SubTexture name="Sans right0002" x="20" y="1982" width="487" height="635"/>
	<SubTexture name="Sans right0003" x="527" y="1982" width="487" height="635"/>
	<SubTexture name="Sans right0004" x="1034" y="1982" width="487" height="635"/>
	<SubTexture name="Sans right0005" x="1541" y="1982" width="487" height="635"/>
	<SubTexture name="Sans right0006" x="2048" y="1982" width="487" height="635"/>
	<SubTexture name="Sans right0007" x="2555" y="1982" width="487" height="635"/>
	<SubTexture name="Sans right0008" x="3062" y="1982" width="487" height="635"/>
	<SubTexture name="Sans right0009" x="3569" y="1982" width="487" height="635"/>
	<SubTexture name="Sans right0010" x="4076" y="1982" width="487" height="635"/>
	<SubTexture name="Sans right0011" x="4583" y="1982" width="487" height="635"/>
	<SubTexture name="Sans right0012" x="5090" y="1982" width="487" height="635"/>
	<SubTexture name="Sans right0013" x="5597" y="1982" width="487" height="635"/>
	<SubTexture name="Sans right0014" x="6104" y="1982" width="487" height="635"/>
	<SubTexture name="Sans up0000" x="20" y="669" width="477" height="654"/>
	<SubTexture name="Sans up0001" x="517" y="669" width="477" height="654"/>
	<SubTexture name="Sans up0002" x="1014" y="669" width="477" height="654"/>
	<SubTexture name="Sans up0003" x="1511" y="669" width="477" height="654"/>
	<SubTexture name="Sans up0004" x="2008" y="669" width="477" height="654"/>
	<SubTexture name="Sans up0005" x="2505" y="669" width="477" height="654"/>
	<SubTexture name="Sans up0006" x="3002" y="669" width="477" height="654"/>
	<SubTexture name="Sans up0007" x="3499" y="669" width="477" height="654"/>
	<SubTexture name="Sans up0008" x="3996" y="669" width="477" height="654"/>
	<SubTexture name="Sans up0009" x="4493" y="669" width="477" height="654"/>
	<SubTexture name="Sans up0010" x="4990" y="669" width="477" height="654"/>
	<SubTexture name="Sans up0011" x="5487" y="669" width="477" height="654"/>
	<SubTexture name="Sans up0012" x="5984" y="669" width="477" height="654"/>
	<SubTexture name="Sans up0013" x="6481" y="669" width="477" height="654"/>
	<SubTexture name="Sans up0014" x="6978" y="669" width="477" height="654"/>
</TextureAtlas>
